urbansim_templates/__init__.py
urbansim_templates/modelmanager.py
urbansim_templates/utils.py
urbansim_templates/models/__init__.py
urbansim_templates/models/binary_logit.py
urbansim_templates/models/large_multinomial_logit.py
urbansim_templates/models/regression.py
urbansim_templates/models/segmented_large_multinomial_logit.py
urbansim_templates/models/shared.py
urbansim_templates/models/small_multinomial_logit.py
urbansim_templates-0.1.4.dist-info/LICENSE.txt
urbansim_templates-0.1.4.dist-info/METADATA
urbansim_templates-0.1.4.dist-info/WHEEL
urbansim_templates-0.1.4.dist-info/top_level.txt
urbansim_templates-0.1.4.dist-info/RECORD
